{"_id":{"$oid":"64280816b524bda49217f7e5"},"name":"Danh thiếp","photo":"public/category/30546df01ff57006652282ab35f4b533fbfce14c.png","numOfProducts":2,"isHidden":false,"createdAt":{"$date":"2023-04-01T10:31:50.388Z"},"updatedAt":{"$date":"2023-04-01T10:03:51.741Z"},"__v":0}
{"_id":{"$oid":"6428080fb524bda49217f7e0"},"name":"Bìa cứng hồ sơ","photo":"public/category/c6e3484ada55faa550c471dc91186c2ea7fa48a4.png","numOfProducts":2,"isHidden":false,"createdAt":{"$date":"2023-04-01T10:31:43.667Z"},"updatedAt":{"$date":"2023-04-01T10:03:51.741Z"},"__v":0}
{"_id":{"$oid":"642808a8b524bda49217f7fd"},"name":"Thiệp mời","photo":"public/category/914755ea39557b39d00b516717146cb1eb537c69.png","numOfProducts":2,"isHidden":false,"createdAt":{"$date":"2023-04-01T10:34:16.232Z"},"updatedAt":{"$date":"2023-04-01T10:03:51.741Z"},"__v":0}
{"_id":{"$oid":"64280887b524bda49217f7f8"},"name":"Ấn phẩm văn phòng","photo":"public/category/1234389a2ac779422379c9f04775410c3c2104d5.png","numOfProducts":0,"isHidden":false,"createdAt":{"$date":"2023-04-01T10:33:43.798Z"},"updatedAt":{"$date":"2023-04-01T10:03:51.741Z"},"__v":0}
{"_id":{"$oid":"6428085bb524bda49217f7f3"},"name":"Vé","photo":"public/category/8dae388205d4ae580f2b05ebc7812b8111d0119e.png","numOfProducts":0,"isHidden":false,"createdAt":{"$date":"2023-04-01T10:32:59.667Z"},"updatedAt":{"$date":"2023-04-01T10:03:51.741Z"},"__v":0}
{"_id":{"$oid":"642808e8b524bda49217f80e"},"name":"Tờ rơi","photo":"public/category/5b023c16f5bbdaab034a3cc64ad50bbdc70f2780.png","numOfProducts":0,"isHidden":false,"createdAt":{"$date":"2023-04-01T10:35:20.034Z"},"updatedAt":{"$date":"2023-04-01T10:03:51.741Z"},"__v":0}
{"_id":{"$oid":"6435789ea1df1d3e5e862a1f"},"name":"Bao thư","photo":"public/category/80f0100bc9ee383cd4e590a938816790b7003ba0.png","numOfProducts":0,"isHidden":false,"createdAt":{"$date":"2023-04-11T15:11:26.373Z"},"updatedAt":{"$date":"2023-04-11T14:59:01.323Z"},"__v":0}
